wgpu_native_installer/__init__.py
wgpu_native_installer/__main__.py
wgpu_native_installer/main.py
wgpu_native_installer/argument/__init__.py
wgpu_native_installer/argument/functions/__init__.py
wgpu_native_installer/argument/functions/public.py
wgpu_native_installer/argument/objects/__init__.py
wgpu_native_installer/argument/objects/argparser.py
wgpu_native_installer/argument/objects/argtype.py
wgpu_native_installer/format/__init__.py
wgpu_native_installer/format/functions/__init__.py
wgpu_native_installer/format/functions/public.py
wgpu_native_installer/format/objects/__init__.py
wgpu_native_installer/format/objects/json.py
wgpu_native_installer/format/objects/markdown.py
wgpu_native_installer/github_release/__init__.py
wgpu_native_installer/github_release/functions/__init__.py
wgpu_native_installer/github_release/functions/public.py
wgpu_native_installer/github_release/objects/__init__.py
wgpu_native_installer/github_release/objects/asset.py
wgpu_native_installer/github_release/objects/data.py
wgpu_native_installer/github_release/objects/meta.py
wgpu_native_installer/unzip/__init__.py
wgpu_native_installer/unzip/functions/__init__.py
wgpu_native_installer/unzip/functions/public.py
wgpu_native_installer/unzip/objects/__init__.py
wgpu_native_installer-0.0.1.dist-info/LICENSE
wgpu_native_installer-0.0.1.dist-info/METADATA
wgpu_native_installer-0.0.1.dist-info/WHEEL
wgpu_native_installer-0.0.1.dist-info/top_level.txt
wgpu_native_installer-0.0.1.dist-info/RECORD
