Metadata-Version: 2.1
Name: wgpu-native-installer
Version: 0.0.1
Summary: Install wgpu-native
Author: Asher Jingkong Chen
License: MIT License
Project-URL: Homepage, https://github.com/AsherJingkongChen/wgpu-native-installer
Project-URL: Repository, https://github.com/AsherJingkongChen/wgpu-native-installer.git
Keywords: wgpu,installer,cli
Classifier: Programming Language :: Python :: 3.8
Classifier: Programming Language :: Python :: 3.12
Classifier: License :: OSI Approved :: MIT License
Classifier: Operating System :: OS Independent
Requires-Python: >=3.8
License-File: LICENSE
Requires-Dist: google-re2 ==1.1
Requires-Dist: httpx[http2] ==0.27.0
Requires-Dist: stream-unzip ==0.0.91
Requires-Dist: tqdm ==4.66.4
